{
  "hookah": [
    {
      "id": 1,
      "image":"https://avatars.mds.yandex.net/get-altay/11409713/2a0000018eae03fcc4c60d430073982a14b6/XXXL",
      "name": "БрикВуд Перл",
      "description": "Уютное место с ароматными кальянами и вкусными коктейлями.",
      "atmosphere": "Просторный зал с мягкими диванами и расслабляющим освещением.",
      "menu": [
        "Табак: Mint, Peach, Apple",
        "Напитки: Чай, Кофе, Соки",
        "Услуги: Мастер-классы, VIP-зоны"
      ],
      "reviews": [
        "Отличное место для отдыха, кальяны просто супер!",
        "Очень уютно, рекомендую для встреч с друзьями."
      ],
      "images": ["https://avatars.mds.yandex.net/get-altay/11409713/2a0000018eae03fcc4c60d430073982a14b6/XXXL", "https://avatars.mds.yandex.net/get-altay/5482016/2a0000017fe54c03eed9cbc12a37bb4feb7d/XXXL"],
      "prices": "Цена кальяна: 1600 руб.",
      "bookingLink": "/book/1",
      "contactInfo": "Телефон: +7 (995) 599-59-66",
      "address": "просп. Героев, 33, Санкт-Петербург"
    },
    {
      "id": 2,
      "image":"https://avatars.mds.yandex.net/get-tycoon/5657946/2a000001843dff02678c110fc98391e0db8d/priority-headline-background",
      "name": "Tangiers Lounge",
      "description": "Помпезный интерьер, VIP-комнаты, PlayStation и мягкие зоны.",
      "atmosphere": "Просторный зал с мягкими диванами и расслабляющим освещением.",
      "menu": [
        "Табак: Mint, Peach, Apple",
        "Напитки: Чай, Кофе, Соки",
        "Услуги: Мастер-классы, VIP-зоны"
      ],
      "reviews": [
        "Отличное место для отдыха, кальяны просто супер!",
        "Очень уютно, рекомендую для встреч с друзьями."
      ],
      "images": ["https://avatars.mds.yandex.net/get-tycoon/5657946/2a000001843dff02678c110fc98391e0db8d/priority-headline-background", "https://avatars.mds.yandex.net/get-altay/15037629/2a00000193c79e9c7d3bbcb6f2f6086ed86d/XXXL"],
      "prices": "Цена кальяна: 1800 руб.",
      "bookingLink": "/book/2",
      "contactInfo": "Телефон: +7 123 456 7890",
      "address": "ул. Катерников, 8, Санкт-Петербург"
    },
    {
      "id": 3,
      "image": "https://avatars.mds.yandex.net/get-altay/4379646/2a00000181caa9b63274cdf4b5024fd822bd/XXXL",
      "name": "Days",
      "description": "Кальян-бар Days — это уютное место с красивым интерьером и потрясающим видом на Финский залив.",
      "atmosphere": "Просторный зал с мягкими диванами и расслабляющим освещением.",
      "menu": [
        "Табак: Mint, Peach, Apple",
        "Напитки: Чай, Кофе, Соки",
        "Услуги: Мастер-классы, VIP-зоны"
      ],
      "reviews": [
        "Отличное место для отдыха, кальяны просто супер!",
        "Очень уютно, рекомендую для встреч с друзьями."
      ],
      "images": ["https://avatars.mds.yandex.net/get-altay/4379646/2a00000181caa9b63274cdf4b5024fd822bd/XXXL", "https://avatars.mds.yandex.net/get-altay/9827107/2a0000018a147a0e44918d8a4c278ca5c5fb/XXXL"],
      "prices": "Цена кальяна: 1500 руб.",
      "bookingLink": "/book/3",
      "contactInfo": "Телефон: +7 (995) 997-91-01",
      "address": "Балтийский бульвар,4, Санкт-Петербург"
    },
    {
      "id": 4,
      "image": "https://avatars.mds.yandex.net/get-altay/9829646/2a00000190eb5f93d2a3f0da471183ab9105/XXXL",
      "name": "Liberty Lounge Bar",
      "description": "Кальян-бар Days — это уютное место с красивым интерьером и потрясающим видом на Финский залив.",
      "atmosphere": "Просторный зал с мягкими диванами и расслабляющим освещением.",
      "menu": [
        "Табак: Mint, Peach, Apple",
        "Напитки: Чай, Кофе, Соки",
        "Услуги: Мастер-классы, VIP-зоны"
      ],
      "reviews": [
        "Отличное место для отдыха, кальяны просто супер!",
        "Очень уютно, рекомендую для встреч с друзьями."
      ],
      "images": ["https://avatars.mds.yandex.net/get-altay/9829646/2a00000190eb5f93d2a3f0da471183ab9105/XXXL", "https://avatars.mds.yandex.net/get-altay/13524363/2a00000190eb5ee85d0e7a226072ef250f5a/XXXL"],
      "prices": "Цена кальяна: 1500 руб.",
      "bookingLink": "/book/4",
      "contactInfo": "Телефон: +7 123 456 7890",
      "address": "наб. Матисова канала, 1, Санкт-Петербург"
    },
    {
      "id": 5,
      "image": "https://avatars.mds.yandex.net/get-altay/13322921/2a00000195e3260d06e40e3d75ce43fe7146/XXXL",
      "name": "Cloud Factory",
      "description": "Cloud Factory — это кальянный бар, где вы можете насладиться дымными кальянами, авторскими чаями и конфетами, а также поиграть в игровые приставки.",
      "atmosphere": "Просторный зал с мягкими диванами и расслабляющим освещением.",
      "menu": [
        "Табак: Mint, Peach, Apple",
        "Напитки: Чай, Кофе, Соки",
        "Услуги: Мастер-классы, VIP-зоны"
      ],
      "reviews": [
        "Отличное место для отдыха, кальяны просто супер!",
        "Очень уютно, рекомендую для встреч с друзьями."
      ],
      "images": ["https://avatars.mds.yandex.net/get-altay/9829646/2a00000190eb5f93d2a3f0da471183ab9105/XXXL", "https://avatars.mds.yandex.net/get-altay/4449685/2a00000181fdee31b80b7882e176891475c5/XXXL"],
      "prices": "Цена кальяна: 1500 руб.",
      "bookingLink": "/book/5",
      "contactInfo": "Телефон: +7 123 456 7890",
      "address": "ул. Адмирала Трибуца, 7, Санкт-Петербург"
    },
    {
      "id": 6,
      "image": "https://avatars.mds.yandex.net/get-altay/9237948/2a00000188cd61faf22eea595216b7746064/XXXL",
      "name": "SmokeTime Lounge",
      "description": "SmokeTime Lounge — это кальянный бар, расположенный на шестом этаже бизнес-центра. Интерьер заведения выполнен в индустриальном стиле, что придает ему особый шарм.",
      "atmosphere": "Просторный зал с мягкими диванами и расслабляющим освещением.",
      "menu": [
        "Табак: Mint, Peach, Apple",
        "Напитки: Чай, Кофе, Соки",
        "Услуги: Мастер-классы, VIP-зоны"
      ],
      "reviews": [
        "Отличное место для отдыха, кальяны просто супер!",
        "Очень уютно, рекомендую для встреч с друзьями."
      ],
      "images": ["https://avatars.mds.yandex.net/get-altay/9237948/2a00000188cd61faf22eea595216b7746064/XXXL", "https://avatars.mds.yandex.net/get-altay/6314780/2a00000188ce5627509136ef09e5fb5a07f4/XXXL"],
      "prices": "Цена кальяна: 1500 руб.",
      "bookingLink": "/book/6",
      "contactInfo": "Телефон: +7 123 456 7890",
      "address": "Брестский бульвар, 8, Санкт-Петербург"
    }
  ]
}